django_subatomic/__init__.py
django_subatomic/_utils.py
django_subatomic/db.py
django_subatomic/py.typed
django_subatomic/test.py
django_subatomic-0.2.0.dist-info/licenses/LICENSE
django_subatomic-0.2.0.dist-info/METADATA
django_subatomic-0.2.0.dist-info/WHEEL
django_subatomic-0.2.0.dist-info/top_level.txt
django_subatomic-0.2.0.dist-info/RECORD
